hmd_cli_mickey/__init__.py
hmd_cli_mickey/controller.py
hmd_cli_mickey/hmd_cli_mickey.py
hmd_cli_mickey/init_files/data/customers.json
hmd_cli_mickey/init_files/data/customers_orders.json
hmd_cli_mickey/init_files/data/orders.json
hmd_cli_mickey/init_files/templates/sql/{{ mickey.src_folder }}/sql/create_table_{{ name }}.sql.j2
hmd_cli_mickey-1.0.51.dist-info/METADATA
hmd_cli_mickey-1.0.51.dist-info/WHEEL
hmd_cli_mickey-1.0.51.dist-info/top_level.txt
hmd_cli_mickey-1.0.51.dist-info/RECORD
