Metadata-Version: 2.1
Name: hmd-cli-mickey
Version: 1.0.51
Summary: General purpose code generator
Home-page: UNKNOWN
Author: Alex Burgoon
Author-email: alex.burgoon@hmdlabs.io
License: Apache 2.0
Platform: UNKNOWN
Requires-Dist: hmd-cli-app
